LICENSE
MANIFEST.in
NOTICE
README.md
requirements.txt
setup.py
navtrix/__init__.py
navtrix/transform.py
navtrix.egg-info/PKG-INFO
navtrix.egg-info/SOURCES.txt
navtrix.egg-info/dependency_links.txt
navtrix.egg-info/top_level.txt