Metadata-Version: 1.1
Name: navtrix
Version: 0.0.3
Summary: Navtrix tracks position and rotation in a Transform class
Home-page: http://github.com/olsoneric/navtrix
Author: Eric Olson
Author-email: me@olsoneric.com
License: Apache 2.0
Keywords: transform,matrix,quaternion
Platform: UNKNOWN
Classifier: Development Status :: 2 - Pre-Alpha
Classifier: License :: OSI Approved :: Apache Software License
Classifier: Programming Language :: Python
Classifier: Programming Language :: Python :: 2.7
